{"num_comments": "39", "date": "July 8, 2022", "username": "comrade_yui", "numLikes": "1466", "rating": "1.0", "profilePhotoLink": "https://a.ltrbxd.com/resized/avatar/twitter/8/3/3/9/9/5/shard/http___pbs.twimg.com_profile_images_1180839569819930625_6NgiJI5c-0-80-0-80-crop.jpg?v=00fc553d0f", "liked": false, "collapsed": false, "text": "<p>christian bale and russell crowe should be ashamed for being here.</p><p>are we sure that natalie portman is a good actress...?</p><p>taikia waititi belongs in the deepest level of director's jail. </p><p>the cavalier laziness at which these films approach emotion and narrative is honestly appalling; everything is in service of a gag, needle drop, or a half-baked cameo, everything, nothing else matters. a visual war crime.</p>", "link": "https://letterboxd.com/comrade_yui/film/thor-love-and-thunder/"}