{"num_comments": "36", "date": "November 23, 2021", "username": "Emma 🔆", "numLikes": "6395", "rating": "4.0", "profilePhotoLink": "https://secure.gravatar.com/avatar/51cbf9a57fd8578b7fbdcf386f39e082?rating=PG&size=80&border=&default=https%3A%2F%2Fs.ltrbxd.com%2Fstatic%2Fimg%2Favatar80-CTtJ8HSs.png", "liked": true, "collapsed": false, "text": " <p>It isn’t right that there are so few films with capybaras. With their quiet beauty and grace, expressive eyes and hypnotic personalities, there is no reason for their appearances in media and merchandise to be so sparse. I will not stand by quietly anymore. The capybara revolution must begin</p> ", "link": "https://letterboxd.com/seahorseronan/film/encanto/"}